browscap/__init__.py
browscap/browscap.py
browscap/converter.py
browscap/loader.py
browscap/parser.py
browscap/pattern_tools.py
browscap/property.py
browscap/quote.py
browscap/subkey_tools.py
browscap/aio/__init__.py
browscap/aio/cache/__init__.py
browscap/aio/cache/redis.py
browscap/cache/__init__.py
browscap/cache/redis.py
browscap_python-0.0.16.dist-info/METADATA
browscap_python-0.0.16.dist-info/RECORD
browscap_python-0.0.16.dist-info/WHEEL
browscap_python-0.0.16.dist-info/top_level.txt
