Metadata-Version: 2.1
Name: browscap-python
Version: 0.0.16
Summary: Python Browscap Library.
Home-page: https://github.com/kvspb/browscap-python
Author: Valery Komarov
Author-email: komarov@valerka.net
License: BSD License
Platform: any
Classifier: Development Status :: 4 - Beta
Classifier: Intended Audience :: Developers
Classifier: License :: OSI Approved :: BSD License
Classifier: Programming Language :: Python :: 2
Classifier: Programming Language :: Python :: 2.6
Classifier: Programming Language :: Python :: 2.7
Classifier: Programming Language :: Python :: 3
Classifier: Programming Language :: Python :: 3.2
Classifier: Programming Language :: Python :: 3.3
Classifier: Programming Language :: Python :: 3.4
Classifier: Programming Language :: Python :: 3.5
Requires-Dist: aioredis
Requires-Dist: fb-re2
Requires-Dist: msgpack-python
Requires-Dist: redis
